shoplift_detector/__init__.py
shoplift_detector/camera_stream.py
shoplift_detector/detection.py
shoplift_detector/main.py
shoplift_detector/video_processor.py
shoplift_detector/models/__init__.py
shoplift_detector/models/lrcn_160S_90_90Q.h5
tests/__init__.py
tests/test_camera_stream.py
tests/test_detection.py
tests/test_video_processor.py
shoplift_detector-1.0.1.dist-info/LICENSE
shoplift_detector-1.0.1.dist-info/METADATA
shoplift_detector-1.0.1.dist-info/WHEEL
shoplift_detector-1.0.1.dist-info/top_level.txt
shoplift_detector-1.0.1.dist-info/RECORD
